LICENSE
MANIFEST.in
README.rst
setup.py
django_yutils.egg-info/PKG-INFO
django_yutils.egg-info/SOURCES.txt
django_yutils.egg-info/dependency_links.txt
django_yutils.egg-info/requires.txt
django_yutils.egg-info/top_level.txt
yutils/__init__.py
yutils/email.py